macer/__init__.py
macer/default.yaml
macer/defaults.py
macer/active_learning/query.py
macer/calculator/__init__.py
macer/calculator/allegro.py
macer/calculator/chgnet.py
macer/calculator/emt.py
macer/calculator/factory.py
macer/calculator/fairchem.py
macer/calculator/m3gnet.py
macer/calculator/mace.py
macer/calculator/mattersim.py
macer/calculator/orb.py
macer/calculator/sevennet.py
macer/cli/__init__.py
macer/cli/interactive.py
macer/cli/main.py
macer/cli/phonopy_main.py
macer/cli/pydefect_main.py
macer/cli/util.py
macer/cli/util_main.py
macer/externals/__init__.py
macer/externals/dynaphopy_bundled/__init__.py
macer/externals/dynaphopy_bundled/atoms.py
macer/externals/dynaphopy_bundled/dynamics.py
macer/externals/dynaphopy_bundled/generate_cell.py
macer/externals/dynaphopy_bundled/parameters.py
macer/externals/dynaphopy_bundled/projection.py
macer/externals/dynaphopy_bundled/analysis/__init__.py
macer/externals/dynaphopy_bundled/analysis/coordinates.py
macer/externals/dynaphopy_bundled/analysis/energy.py
macer/externals/dynaphopy_bundled/analysis/modes.py
macer/externals/dynaphopy_bundled/analysis/peaksearch.py
macer/externals/dynaphopy_bundled/analysis/thermal_properties.py
macer/externals/dynaphopy_bundled/analysis/fitting/__init__.py
macer/externals/dynaphopy_bundled/analysis/fitting/fitting_functions.py
macer/externals/dynaphopy_bundled/c/__init__.py
macer/externals/dynaphopy_bundled/interface/__init__.py
macer/externals/dynaphopy_bundled/interface/interactive_ui.py
macer/externals/dynaphopy_bundled/interface/lammps_link.py
macer/externals/dynaphopy_bundled/interface/phonopy_link.py
macer/externals/dynaphopy_bundled/interface/iofile/__init__.py
macer/externals/dynaphopy_bundled/interface/iofile/trajectory_parsers.py
macer/externals/dynaphopy_bundled/power_spectrum/__init__.py
macer/externals/e3nn_legacy/__init__.py
macer/externals/e3nn_legacy/io/__init__.py
macer/externals/e3nn_legacy/io/_cartesian_tensor.py
macer/externals/e3nn_legacy/io/_spherical_tensor.py
macer-0.2.0.dist-info/licenses/LICENSE
macer-0.2.0.dist-info/METADATA
macer-0.2.0.dist-info/WHEEL
macer-0.2.0.dist-info/entry_points.txt
macer-0.2.0.dist-info/top_level.txt
macer-0.2.0.dist-info/RECORD
