Metadata-Version: 2.4
Name: macer
Version: 0.2.0
Summary: Machine-learning accelerated Atomic Computational Environment for automated Research workflows
Author-email: Soungmin Bae <soungminbae@gmail.com>
License: MIT
Requires-Python: >=3.10
License-File: LICENSE
Requires-Dist: numpy
Requires-Dist: matplotlib
Requires-Dist: ase
Requires-Dist: pymatgen
Requires-Dist: emmet-core
Requires-Dist: monty
Requires-Dist: phonopy==2.47.1
Requires-Dist: phono3py==3.24.0
Requires-Dist: seekpath==2.1.0
Requires-Dist: vise==0.9.5
Requires-Dist: pydefect==0.9.11
Requires-Dist: dynaphopy==1.18.0
Requires-Dist: symfc
Requires-Dist: scipy
Requires-Dist: tqdm
Requires-Dist: pyyaml
Requires-Dist: torch
Requires-Dist: torch_ema
Requires-Dist: typing-extensions
Requires-Dist: e3nn>=0.5.1
Requires-Dist: chgnet
Requires-Dist: matgl
Requires-Dist: mattersim
Requires-Dist: sevenn
Requires-Dist: fairchem-core
Requires-Dist: orb-models
Requires-Dist: nequip
Requires-Dist: huggingface_hub
Dynamic: license-file
